{
  "project_info": {
    "project_number": "709692300821",
    "firebase_url": "https://book-my-etaxi-default-rtdb.asia-southeast1.firebasedatabase.app",
    "project_id": "book-my-etaxi",
    "storage_bucket": "book-my-etaxi.appspot.com"
  },
  "client": [
    {
      "client_info": {
        "mobilesdk_app_id": "1:709692300821:android:f7ca396b04a1070a29381c",
        "android_client_info": {
          "package_name": "com.bmet.customerapp"
        }
      },
      "oauth_client": [
        {
          "client_id": "709692300821-jh6gn6eeglb23r7gdij5qneisr32vrok.apps.googleusercontent.com",
          "client_type": 1,
          "android_info": {
            "package_name": "com.bmet.customerapp",
            "certificate_hash": "67090bde9c9c37a397ab02913db9d214a4bb59e2"
          }
        },
        {
          "client_id": "709692300821-qcoj1kl1jomtigkremvp8rn2msdkgg5r.apps.googleusercontent.com",
          "client_type": 1,
          "android_info": {
            "package_name": "com.bmet.customerapp",
            "certificate_hash": "2a52fdc935ff1154ce6b72d4d7fc1733e14e6b63"
          }
        },
        {
          "client_id": "709692300821-4bmpccgvpo33ccdj1gdjgfeivl7hjbqu.apps.googleusercontent.com",
          "client_type": 3
        }
      ],
      "api_key": [
        {
          "current_key": "AIzaSyAmhfTVZULPMgosgbUaZLgdOvkpXRUisO4"
        }
      ],
      "services": {
        "appinvite_service": {
          "other_platform_oauth_client": [
            {
              "client_id": "709692300821-4bmpccgvpo33ccdj1gdjgfeivl7hjbqu.apps.googleusercontent.com",
              "client_type": 3
            }
          ]
        }
      }
    },
    {
      "client_info": {
        "mobilesdk_app_id": "1:709692300821:android:44701ce37cbf921929381c",
        "android_client_info": {
          "package_name": "com.bmet.driver_app"
        }
      },
      "oauth_client": [
        {
          "client_id": "709692300821-gqtlmu01jkeh7eakseni7nhap5fmcp65.apps.googleusercontent.com",
          "client_type": 1,
          "android_info": {
            "package_name": "com.bmet.driver_app",
            "certificate_hash": "10652ff96b2af7cf3ebf5ad1abcad01b3dffdc23"
          }
        },
        {
          "client_id": "709692300821-u1jd6dv0traqtppuuivskvgmq1l3ijr6.apps.googleusercontent.com",
          "client_type": 1,
          "android_info": {
            "package_name": "com.bmet.driver_app",
            "certificate_hash": "67090bde9c9c37a397ab02913db9d214a4bb59e2"
          }
        },
        {
          "client_id": "709692300821-4bmpccgvpo33ccdj1gdjgfeivl7hjbqu.apps.googleusercontent.com",
          "client_type": 3
        }
      ],
      "api_key": [
        {
          "current_key": "AIzaSyAmhfTVZULPMgosgbUaZLgdOvkpXRUisO4"
        }
      ],
      "services": {
        "appinvite_service": {
          "other_platform_oauth_client": [
            {
              "client_id": "709692300821-4bmpccgvpo33ccdj1gdjgfeivl7hjbqu.apps.googleusercontent.com",
              "client_type": 3
            }
          ]
        }
      }
    }
  ],
  "configuration_version": "1"
}